twse/__init__.py
twse/py.typed
twse/stock_info.py
twse/utils.py
twse-0.4.0.dist-info/METADATA
twse-0.4.0.dist-info/WHEEL
twse-0.4.0.dist-info/licenses/LICENSE
twse-0.4.0.dist-info/RECORD
