Metadata-Version: 2.4
Name: twse
Version: 0.4.0
Author-email: narumi <toucans-cutouts0f@icloud.com>
License-File: LICENSE
Requires-Python: >=3.12
Requires-Dist: httpx>=0.27.2
Requires-Dist: loguru>=0.7.3
Requires-Dist: pydantic>=2.11.2
